LICENSE
MANIFEST.in
README.md
setup.py
DipperAI_inner/__init__.py
DipperAI_inner/main.py
DipperAI_inner/version.py
DipperAI_inner.egg-info/PKG-INFO
DipperAI_inner.egg-info/SOURCES.txt
DipperAI_inner.egg-info/dependency_links.txt
DipperAI_inner.egg-info/requires.txt
DipperAI_inner.egg-info/top_level.txt
DipperAI_inner/maas/__init__.py
DipperAI_inner/maas/aigcaas.py
DipperAI_inner/maas/core.py
DipperAI_inner/maas/huggingface.py
DipperAI_inner/maas/modelscope.py
DipperAI_inner/resources/__init__.py
DipperAI_inner/resources/config.py
DipperAI_inner/utils/__init__.py
DipperAI_inner/utils/cache.py
DipperAI_inner/utils/common.py
DipperAI_inner/utils/logger.py
DipperAI_inner/vendor/__init__.py
DipperAI_inner/vendor/alibaba.py
DipperAI_inner/vendor/aws.py
DipperAI_inner/vendor/local.py