Metadata-Version: 2.1
Name: DipperAI-inner
Version: 0.0.2
Summary: DipperAI inner package
Home-page: https://github.com/DipperAI/DipperAI
Author: jiaw127
Author-email: jiaw127@163.com
License: MIT
Classifier: License :: OSI Approved :: MIT License
Classifier: Programming Language :: Python
Classifier: Programming Language :: Python :: 3
Classifier: Programming Language :: Python :: 3.10
Requires-Python: >=3.10.0
License-File: LICENSE
Requires-Dist: colorama==0.4.6
Requires-Dist: Requests==2.31.0
Requires-Dist: ruff==0.2.2
Requires-Dist: pre-commit==3.6.2
